dist/__init__.py
dist/main.py
module/__init__.py
module/main.py
EzCalc-1.0.0.dist-info/LICENSE
EzCalc-1.0.0.dist-info/METADATA
EzCalc-1.0.0.dist-info/WHEEL
EzCalc-1.0.0.dist-info/top_level.txt
EzCalc-1.0.0.dist-info/zip-safe
EzCalc-1.0.0.dist-info/RECORD
