Metadata-Version: 2.1
Name: EzCalc
Version: 1.0.0
Summary: A Basic Calculator With Many Functions
Home-page: https://github.com/jacebillingsley
Author: Jace Billingsley
Author-email: jacebphotography@Outlook.com
License: MIT License
Platform: UNKNOWN
Classifier: Programming Language :: Python :: 3
Classifier: License :: OSI Approved :: MIT License
Classifier: Operating System :: OS Independent
Requires-Python: >=3.0
